kafkautil.py
kafkautil_ecs-1.0.0.dist-info/LICENSE.txt
kafkautil_ecs-1.0.0.dist-info/METADATA
kafkautil_ecs-1.0.0.dist-info/WHEEL
kafkautil_ecs-1.0.0.dist-info/entry_points.txt
kafkautil_ecs-1.0.0.dist-info/top_level.txt
kafkautil_ecs-1.0.0.dist-info/RECORD
