Metadata-Version: 2.1
Name: kafkautil-ecs
Version: 1.0.0
Summary: UNKNOWN
Home-page: UNKNOWN
Author: Ryan Gilmore
Author-email: ryan.gilmore@ecstech.com
License: UNKNOWN
Platform: UNKNOWN
Classifier: Intended Audience :: Developers
Classifier: Topic :: Software Development :: Build Tools
Classifier: License :: OSI Approved :: MIT License
Classifier: Programming Language :: Python :: 3
Requires-Dist: Click
Requires-Dist: kafka-python
